<?xml version="1.0" encoding="UTF-8"?>
<algebra xmlns:typ="http://www.entitymodelling.org/theory/type"
         xmlns:trm="http://www.entitymodelling.org/theory/term"
         xmlns="http://www.entitymodelling.org/theory/term">
	
  <name>ccseq</name>

  <rewriteRule>
      <id>3s</id>
      <lhs>
         <o id="o1" context="self::*">
            <seq id="f1_1"
                 xpath="$o1/child::*[position() &lt; $o2/count(preceding-sibling::*) + 1]">f1</seq>
            <o id="o2" context="$o1/child::o">
               <seq id="f2_1" xpath="$o2/child::*">f2</seq>
            </o>
            <seq id="f3_1"
                 xpath="$o1/child::*[position() &gt; $o2/count(preceding-sibling::*) + 1]">f3</seq>
         </o>
      </lhs>
      <rhs>
         <o>
            <seq>f1</seq>
            <seq>f2</seq>
            <seq>f3</seq>
         </o>
      </rhs>
  </rewriteRule>

  <rewriteRule>
      <id>3sp</id>
      <lhs>
         <o id="o4" context="self::*">
            <var id="f_1" context="$o4/child::*[1][not(following-sibling::*)]">f</var>
         </o>
      </lhs>
      <rhs>
         <var>f</var>
      </rhs>
  </rewriteRule>


  <rewriteRule>
      <id>5</id>
      <lhs>
         <star id="star1" context="self::*">
            <var id="f_1" context="$star1/child::*[1]">f</var>
            <star id="star2"
                  context="$f_1/following-sibling::*[1][self::star][not(following-sibling::*)]">
               <var id="g_1" context="$star2/child::*[1]">g</var>
               <var id="x_1"
                    context="$g_1/following-sibling::*[1][not(following-sibling::*)]">x</var>
            </star>
         </star>
      </lhs>
      <rhs>
         <star>
            <o>
               <var>f</var>
               <var>g</var>
            </o>
            <var>x</var>
         </star>
      </rhs>
  </rewriteRule>

  <rewriteRule>
      <id>6ps</id>
      <lhs>
         <o id="o6" context="self::*">
            <seq id="h1_1"
                 xpath="$o6/child::*[position() &lt; $q1/count(preceding-sibling::*) + 1]">h1</seq>
            <q id="q1" context="$o6/child::q">
               <var id="f_1" context="$q1/child::*[1]">f</var>
               <star id="star4"
                     context="$f_1/following-sibling::*[1][self::star][not(following-sibling::*)]">
                  <var id="g_1" context="$star4/child::*[1]">g</var>
                  <var id="x_1"
                       context="$g_1/following-sibling::*[1][not(following-sibling::*)]">x</var>
               </star>
            </q>
            <q id="q2" context="$q1/following-sibling::*[1][self::q]">
               <var id="g_2" context="$q2/child::*[1]">g</var>
               <var id="x_2"
                    context="$g_2/following-sibling::*[1][not(following-sibling::*)]">x</var>
            </q>
            <seq id="h2_1"
                 xpath="$o6/child::*[position() &gt; $q2/count(preceding-sibling::*) + 1]">h2</seq>
         </o>
      </lhs>
      <rhs>
         <o>
            <seq>h1</seq>
            <q>
               <o>
                  <var>f</var>
                  <var>g</var>
               </o>
               <var>x</var>
            </q>
            <seq>h2</seq>
         </o>
      </rhs>
  </rewriteRule>

  <rewriteRule>
      <id>7</id>
      <lhs>      
         <star id="star5" context="self::*">
            <o id="o9" context="$star5/child::*[1][self::o][not(child::*)]"/>
            <var id="x_1"
                 context="$o9/following-sibling::*[1][not(following-sibling::*)]">x</var>
         </star>       
      </lhs>
      <rhs>
         <var>x</var>
      </rhs>
  </rewriteRule>

  <rewriteRule>
      <id>8</id>
      <lhs>      
         <q id="q4" context="self::*">
            <o id="o10" context="$q4/child::*[1][self::o][not(child::*)]"/>
            <var id="x_1"
                 context="$o10/following-sibling::*[1][not(following-sibling::*)]">x</var>
         </q>       
      </lhs>
      <rhs>
         <o/>
      </rhs>
  </rewriteRule>

  <rewriteRule>
      <id>9ps</id>
      <lhs>
         <o id="o12" context="self::*">
            <seq id="h1_1"
                 xpath="$o12/child::*[position() &lt; $q5/count(preceding-sibling::*) + 1]">h1</seq>
            <q id="q5" context="$o12/child::q">
               <var id="f_1" context="$q5/child::*[1]">f</var>
               <var id="y_1"
                    context="$f_1/following-sibling::*[1][not(following-sibling::*)]">y</var>
            </q>
            <p id="p1" context="$q5/following-sibling::*[1][self::p][not(child::*)]"/>
            <seq id="h2_1"
                 xpath="$o12/child::*[position() &gt; $p1/count(preceding-sibling::*) + 1]">h2</seq>
         </o>
      </lhs>
      <rhs>
         <o>
            <seq>h1</seq>
            <p/>
            <var>f</var>
            <seq>h2</seq>
         </o>
      </rhs>
  </rewriteRule>

  <rewriteRule>
      <id>10ps</id>
      <lhs>
         <o id="o14" context="self::*">
            <seq id="h1_1"
                 xpath="$o14/child::*[position() &lt; $s1/count(preceding-sibling::*) + 1]">h1</seq>
            <s id="s1" context="$o14/child::s">
               <var id="f_1" context="$s1/child::*[1][not(following-sibling::*)]">f</var>
            </s>
            <p id="p3" context="$s1/following-sibling::*[1][self::p][not(child::*)]"/>
            <seq id="h2_1"
                 xpath="$o14/child::*[position() &gt; $p3/count(preceding-sibling::*) + 1]">h2</seq>
         </o>
      </lhs>
      <rhs>
         <o>
            <seq>h1</seq>
            <seq>h2</seq>
         </o>
      </rhs>
  </rewriteRule>


  <rewriteRule>
      <id>11pps</id>
      <lhs>
         <o id="o16" context="self::*">
            <seq id="h1_1"
                 xpath="$o16/child::*[position() &lt; $s2/count(preceding-sibling::*) + 1]">h1</seq>
            <s id="s2" context="$o16/child::s">
               <var id="f_1" context="$s2/child::*[1][not(following-sibling::*)]">f</var>
            </s>
            <q id="q6" context="$s2/following-sibling::*[1][self::q]">
               <o id="o17" context="$q6/child::*[1][self::o]">
                  <var id="f_2" context="$o17/child::*[1]">f</var>
                  <p id="p4"
                     context="$f_2/following-sibling::*[1][self::p][not(following-sibling::*)][not(child::*)]"/>
               </o>
               <var id="y_1"
                    context="$o17/following-sibling::*[1][not(following-sibling::*)]">y</var>
            </q>
            <seq id="h2_1"
                 xpath="$o16/child::*[position() &gt; $q6/count(preceding-sibling::*) + 1]">h2</seq>
         </o>
      </lhs>
      <rhs>
         <o>
            <seq>h1</seq>
            <var>f</var>
            <seq>h2</seq>
         </o>
      </rhs>
  </rewriteRule>

  <rewriteRule>
      <id>11pps.id</id>
      <lhs>
         <o id="o19" context="self::*">
            <seq id="h1_1"
                 xpath="$o19/child::*[position() &lt; $s3/count(preceding-sibling::*) + 1]">h1</seq>
            <s id="s3" context="$o19/child::s">
               <o id="o20"
                  context="$s3/child::*[1][self::o][not(following-sibling::*)][not(child::*)]">
          </o>
            </s>
            <q id="q7" context="$s3/following-sibling::*[1][self::q]">
               <p id="p5" context="$q7/child::*[1][self::p][not(child::*)]"/>
               <var id="y_1"
                    context="$p5/following-sibling::*[1][not(following-sibling::*)]">y</var>
            </q>
            <seq id="h2_1"
                 xpath="$o19/child::*[position() &gt; $q7/count(preceding-sibling::*) + 1]">h2</seq>
         </o>
      </lhs>
      <rhs>
         <o>
            <seq>h1</seq>
            <seq>h2</seq>
         </o>
      </rhs>
  </rewriteRule>

  <rewriteRule>
      <id>11pps2</id>
      <lhs>
         <o id="o22" context="self::*">
            <seq id="h1_1"
                 xpath="$o22/child::*[position() &lt; $s4/count(preceding-sibling::*) + 1]">h1</seq>
            <s id="s4" context="$o22/child::s">
               <o id="o23" context="$s4/child::*[1][self::o][not(following-sibling::*)]">
                  <seq id="h2_1" xpath="$o23/child::*">h2</seq>
               </o>
            </s>
            <q id="q8" context="$s4/following-sibling::*[1][self::q]">
               <o id="o24" context="$q8/child::*[1][self::o]">
                  <seq id="h2_2"
                       xpath="$o24/child::*[position() &lt; $p6/count(preceding-sibling::*) + 1]">h2</seq>
                  <p id="p6"
                     context="$o24/child::p[not(following-sibling::*)][not(child::*)]"/>
               </o>
               <var id="y_1"
                    context="$o24/following-sibling::*[1][not(following-sibling::*)]">y</var>
            </q>
            <seq id="h3_1"
                 xpath="$o22/child::*[position() &gt; $q8/count(preceding-sibling::*) + 1]">h3</seq>
         </o>
      </lhs>
      <rhs>
         <o>
            <seq>h1</seq>
            <o>
               <seq>h2</seq>
            </o>
            <seq>h3</seq>
         </o>
      </rhs>
  </rewriteRule>

  <rewriteRule>
      <id>11pps3</id>
      <lhs>
         <o id="o27" context="self::*">
            <seq id="h1_1"
                 xpath="$o27/child::*[position() &lt; $s5/count(preceding-sibling::*) + 1]">h1</seq>
            <s id="s5" context="$o27/child::s">
               <o id="o28" context="$s5/child::*[1][self::o][not(following-sibling::*)]">
                  <seq id="h2_1" xpath="$o28/child::*">h2</seq>
               </o>
            </s>
            <q id="q9" context="$s5/following-sibling::*[1][self::q]">
               <o id="o29" context="$q9/child::*[1][self::o]">
                  <seq id="h2_2"
                       xpath="$o29/child::*[position() &lt; $p7/count(preceding-sibling::*) + 1]">h2</seq>
                  <p id="p7" context="$o29/child::p[not(child::*)]"/>
                  <seq id="h3_1"
                       xpath="$o29/child::*[position() &gt; $p7/count(preceding-sibling::*) + 1]">h3</seq>
               </o>
               <var id="y_1"
                    context="$o29/following-sibling::*[1][not(following-sibling::*)]">y</var>
            </q>
            <seq id="h4_1"
                 xpath="$o27/child::*[position() &gt; $q9/count(preceding-sibling::*) + 1]">h4</seq>
         </o>
      </lhs>
      <rhs>
         <o>
            <seq>h1</seq>
            <o>
               <seq>h2</seq>
            </o>
            <q>
               <o>
                  <seq>h3</seq>
               </o>
               <var>y</var>
            </q>
            <seq>h4</seq>
         </o>
      </rhs>
  </rewriteRule>

  <rewriteRule>
      <id>11pps4</id>
      <lhs>
         <o id="o33" context="self::*">
            <seq id="h1_1"
                 xpath="$o33/child::*[position() &lt; $s6/count(preceding-sibling::*) + 1]">h1</seq>
            <s id="s6" context="$o33/child::s">
               <var id="ff_1" context="$s6/child::*[1][not(following-sibling::*)]">ff</var>
            </s>
            <q id="q11" context="$s6/following-sibling::*[1][self::q]">
               <o id="o34" context="$q11/child::*[1][self::o]">
                  <var id="ff_2" context="$o34/child::*[1]">ff</var>
                  <p id="p8" context="$ff_2/following-sibling::*[1][self::p][not(child::*)]"/>
                  <seq id="h2_1"
                       xpath="$o34/child::*[position() &gt; $p8/count(preceding-sibling::*) + 1]">h2</seq>
               </o>
               <var id="y_1"
                    context="$o34/following-sibling::*[1][not(following-sibling::*)]">y</var>
            </q>
            <seq id="h3_1"
                 xpath="$o33/child::*[position() &gt; $q11/count(preceding-sibling::*) + 1]">h3</seq>
         </o>
      </lhs>
      <rhs>
         <o>
            <seq>h1</seq>
            <var>ff</var>
            <q>
               <o>
                  <seq>h2</seq>
               </o>
               <var>y</var>
            </q>
            <seq>h3</seq>
         </o>
      </rhs>
  </rewriteRule>

  <rewriteRule>
      <id>12s</id>
      <lhs>
         <s id="s7" context="self::*">
            <o id="o37" context="$s7/child::*[1][self::o][not(following-sibling::*)]">
               <seq id="f_1"
                    xpath="$o37/child::*[position() &lt; $q13/count(preceding-sibling::*) + 1]">f</seq>
               <q id="q13" context="$o37/child::q[not(following-sibling::*)]">
                  <var id="g_1" context="$q13/child::*[1]">g</var>
                  <var id="z_1"
                       context="$g_1/following-sibling::*[1][not(following-sibling::*)]">z</var>
               </q>
            </o>
         </s>
      </lhs>
      <rhs>
         <s>
            <o>
               <seq>f</seq>
            </o>
         </s>
      </rhs>
  </rewriteRule> 

  <rewriteRule>
      <id>17s</id>
      <lhs>
         <o id="o39" context="self::*">
            <seq id="h1_1"
                 xpath="$o39/child::*[position() &lt; $s9/count(preceding-sibling::*) + 1]">h1</seq>
            <s id="s9" context="$o39/child::s">
               <o id="o40" context="$s9/child::*[1][self::o][not(following-sibling::*)]">
                  <var id="f_1" context="$o40/child::*[1]">f</var>
                  <s id="s10"
                     context="$f_1/following-sibling::*[1][self::s][not(following-sibling::*)]">
                     <var id="g_1" context="$s10/child::*[1][not(following-sibling::*)]">g</var>
                  </s>
               </o>
            </s>
            <q id="q14" context="$s9/following-sibling::*[1][self::q]">
               <var id="f_2" context="$q14/child::*[1]">f</var>
               <star id="star6"
                     context="$f_2/following-sibling::*[1][self::star][not(following-sibling::*)]">
                  <o id="o41" context="$star6/child::*[1][self::o]">
                     <var id="g_2" context="$o41/child::*[1]">g</var>
                     <p id="p9"
                        context="$g_2/following-sibling::*[1][self::p][not(following-sibling::*)][not(child::*)]"/>
                  </o>
                  <var id="c_1"
                       context="$o41/following-sibling::*[1][not(following-sibling::*)]">c</var>
               </star>
            </q>
            <seq id="h2_1"
                 xpath="$o39/child::*[position() &gt; $q14/count(preceding-sibling::*) + 1]">h2</seq>
         </o>    
      </lhs>
      <rhs>
         <o>
            <seq>h1</seq>
            <var>f</var>
            <s>
               <var>g</var>
            </s>
            <seq>h2</seq>
         </o>
      </rhs>
  </rewriteRule>


  <rewriteRule>
      <id>17ss</id>
      <lhs>
         <o id="o43" context="self::*">
            <seq id="h1_1"
                 xpath="$o43/child::*[position() &lt; $s12/count(preceding-sibling::*) + 1]">h1</seq>
            <s id="s12" context="$o43/child::s">
               <o id="o44" context="$s12/child::*[1][self::o][not(following-sibling::*)]">
                  <seq id="f_1"
                       xpath="$o44/child::*[position() &lt; $s13/count(preceding-sibling::*) + 1]">f</seq>
                  <s id="s13" context="$o44/child::s[not(following-sibling::*)]">
                     <var id="g_1" context="$s13/child::*[1][not(following-sibling::*)]">g</var>
                  </s>
               </o>
            </s>
            <q id="q15" context="$s12/following-sibling::*[1][self::q]">
               <o id="o45" context="$q15/child::*[1][self::o]">
                  <seq id="f_2" xpath="$o45/child::*">f</seq>
               </o>
               <star id="star7"
                     context="$o45/following-sibling::*[1][self::star][not(following-sibling::*)]">
                  <o id="o46" context="$star7/child::*[1][self::o]">
                     <var id="g_2" context="$o46/child::*[1]">g</var>
                     <p id="p10"
                        context="$g_2/following-sibling::*[1][self::p][not(following-sibling::*)][not(child::*)]"/>
                  </o>
                  <var id="c_1"
                       context="$o46/following-sibling::*[1][not(following-sibling::*)]">c</var>
               </star>
            </q>
            <seq id="h2_1"
                 xpath="$o43/child::*[position() &gt; $q15/count(preceding-sibling::*) + 1]">h2</seq>
         </o>    
      </lhs>
      <rhs>
         <o>
            <seq>h1</seq>
            <seq>f</seq>
            <s>
               <var>g</var>
            </s>
            <seq>h2</seq>
         </o>
      </rhs>
  </rewriteRule>

  
  <rewriteRule>
      <id>17sss</id>
      <lhs>
         <o id="o48" context="self::*">
            <seq id="h1_1"
                 xpath="$o48/child::*[position() &lt; $s15/count(preceding-sibling::*) + 1]">h1</seq>
            <s id="s15" context="$o48/child::s">
               <o id="o49" context="$s15/child::*[1][self::o][not(following-sibling::*)]">
                  <var id="f_1" context="$o49/child::*[1]">f</var>
                  <s id="s16"
                     context="$f_1/following-sibling::*[1][self::s][not(following-sibling::*)]">
                     <o id="o50" context="$s16/child::*[1][self::o][not(following-sibling::*)]">
                        <seq id="g_1" xpath="$o50/child::*">g</seq>
                     </o>
                  </s>
               </o>
            </s>
            <q id="q16" context="$s15/following-sibling::*[1][self::q]">
               <var id="f_2" context="$q16/child::*[1]">f</var>
               <star id="star8"
                     context="$f_2/following-sibling::*[1][self::star][not(following-sibling::*)]">
                  <o id="o51" context="$star8/child::*[1][self::o]">
                     <seq id="g_2"
                          xpath="$o51/child::*[position() &lt; $p11/count(preceding-sibling::*) + 1]">g</seq>
                     <p id="p11"
                        context="$o51/child::p[not(following-sibling::*)][not(child::*)]"/>
                  </o>
                  <var id="c_1"
                       context="$o51/following-sibling::*[1][not(following-sibling::*)]">c</var>
               </star>
            </q>
            <seq id="h2_1"
                 xpath="$o48/child::*[position() &gt; $q16/count(preceding-sibling::*) + 1]">h2</seq>
         </o>    
      </lhs>
      <rhs>
         <o>
            <seq>h1</seq>
            <var>f</var>
            <s>
               <o>
                  <seq>g</seq>
               </o>
            </s>
            <seq>h2</seq>
         </o>
      </rhs>
  </rewriteRule>

  <rewriteRule>
      <id>17ssss</id>
      <lhs>
         <o id="o54" context="self::*">
            <seq id="h1_1"
                 xpath="$o54/child::*[position() &lt; $s18/count(preceding-sibling::*) + 1]">h1</seq>
            <s id="s18" context="$o54/child::s">
               <o id="o55" context="$s18/child::*[1][self::o][not(following-sibling::*)]">
                  <seq id="f_1"
                       xpath="$o55/child::*[position() &lt; $s19/count(preceding-sibling::*) + 1]">f</seq>
                  <s id="s19" context="$o55/child::s[not(following-sibling::*)]">
                     <o id="o56" context="$s19/child::*[1][self::o][not(following-sibling::*)]">
                        <seq id="g_1" xpath="$o56/child::*">g</seq>
                     </o>
                  </s>
               </o>
            </s>
            <q id="q17" context="$s18/following-sibling::*[1][self::q]">
               <o id="o57" context="$q17/child::*[1][self::o]">
                  <seq id="f_2" xpath="$o57/child::*">f</seq>
               </o>
               <star id="star9"
                     context="$o57/following-sibling::*[1][self::star][not(following-sibling::*)]">
                  <o id="o58" context="$star9/child::*[1][self::o]">
                     <seq id="g_2"
                          xpath="$o58/child::*[position() &lt; $p12/count(preceding-sibling::*) + 1]">g</seq>
                     <p id="p12"
                        context="$o58/child::p[not(following-sibling::*)][not(child::*)]"/>
                  </o>
                  <var id="c_1"
                       context="$o58/following-sibling::*[1][not(following-sibling::*)]">c</var>
               </star>
            </q>
            <seq id="h2_1"
                 xpath="$o54/child::*[position() &gt; $q17/count(preceding-sibling::*) + 1]">h2</seq>
         </o>    
      </lhs>
      <rhs>
         <o>
            <seq>h1</seq>
            <seq>f</seq>
            <s>
               <o>
                  <seq>g</seq>
               </o>
            </s>
            <seq>h2</seq>
         </o>
      </rhs>
  </rewriteRule>


  <rewriteRule>
      <id>17s.id</id>
      <lhs>
         <o id="o61" context="self::*">
            <seq id="h1_1"
                 xpath="$o61/child::*[position() &lt; $s21/count(preceding-sibling::*) + 1]">h1</seq>
            <s id="s21" context="$o61/child::s">
               <o id="o62" context="$s21/child::*[1][self::o][not(following-sibling::*)]">
                  <var id="f_1" context="$o62/child::*[1]">f</var>
                  <s id="s22"
                     context="$f_1/following-sibling::*[1][self::s][not(following-sibling::*)]">
                     <o id="o63"
                        context="$s22/child::*[1][self::o][not(following-sibling::*)][not(child::*)]">
              </o>
                  </s>
               </o>
            </s>
            <q id="q18" context="$s21/following-sibling::*[1][self::q]">
               <var id="f_2" context="$q18/child::*[1]">f</var>
               <star id="star10"
                     context="$f_2/following-sibling::*[1][self::star][not(following-sibling::*)]">
                  <p id="p13" context="$star10/child::*[1][self::p][not(child::*)]"/>
                  <var id="c_1"
                       context="$p13/following-sibling::*[1][not(following-sibling::*)]">c</var>
               </star>
            </q>
            <seq id="h2_1"
                 xpath="$o61/child::*[position() &gt; $q18/count(preceding-sibling::*) + 1]">h2</seq>
         </o>    
      </lhs>
      <rhs>
         <o>
            <seq>h1</seq>
            <var>f</var>
            <s>
               <o>
          </o>
            </s>
            <seq>h2</seq>
         </o>
      </rhs>
  </rewriteRule>


  <rewriteRule>
      <id>17ss.id</id>
      <lhs>
         <o id="o66" context="self::*">
            <seq id="h1_1"
                 xpath="$o66/child::*[position() &lt; $s24/count(preceding-sibling::*) + 1]">h1</seq>
            <s id="s24" context="$o66/child::s">
               <o id="o67" context="$s24/child::*[1][self::o][not(following-sibling::*)]">
                  <seq id="f_1"
                       xpath="$o67/child::*[position() &lt; $s25/count(preceding-sibling::*) + 1]">f</seq>
                  <s id="s25" context="$o67/child::s[not(following-sibling::*)]">
                     <o id="o68"
                        context="$s25/child::*[1][self::o][not(following-sibling::*)][not(child::*)]">
              </o>
                  </s>
               </o>
            </s>
            <q id="q19" context="$s24/following-sibling::*[1][self::q]">
               <o id="o69" context="$q19/child::*[1][self::o]">
                  <seq id="f_2" xpath="$o69/child::*">f</seq>
               </o>
               <star id="star11"
                     context="$o69/following-sibling::*[1][self::star][not(following-sibling::*)]">
                  <p id="p14" context="$star11/child::*[1][self::p][not(child::*)]"/>
                  <var id="c_1"
                       context="$p14/following-sibling::*[1][not(following-sibling::*)]">c</var>
               </star>
            </q>
            <seq id="h2_1"
                 xpath="$o66/child::*[position() &gt; $q19/count(preceding-sibling::*) + 1]">h2</seq>
         </o>    
      </lhs>
      <rhs>
         <o>
            <seq>h1</seq>
            <seq>f</seq>
            <s>
               <o>
          </o>
            </s>
            <seq>h2</seq>
         </o>
      </rhs>
  </rewriteRule>


  <rewriteRule>
      <id>21</id>
      <lhs>
         <s id="s27" context="self::*">
            <s id="s28" context="$s27/child::*[1][self::s][not(following-sibling::*)]">
               <var id="f_1" context="$s28/child::*[1][not(following-sibling::*)]">f</var>
            </s>
         </s>	
      </lhs>
      <rhs>
         <s>
            <var>f</var>
         </s>
      </rhs>
  </rewriteRule>


  <rewriteRule>
      <id>26</id>
      <lhs>      
         <s id="s30" context="self::*">
            <q id="q20" context="$s30/child::*[1][self::q][not(following-sibling::*)]">
               <var id="g_1" context="$q20/child::*[1]">g</var>
               <var id="z_1"
                    context="$g_1/following-sibling::*[1][not(following-sibling::*)]">z</var>
            </q>
         </s>       
      </lhs>
      <rhs>
         <s>
            <o/>
         </s>
      </rhs>
  </rewriteRule>

  <rewriteRule>
      <id>28s</id>
      <lhs>
         <o id="o73" context="self::*">
            <seq id="h1_1"
                 xpath="$o73/child::*[position() &lt; $s32/count(preceding-sibling::*) + 1]">h1</seq>
            <s id="s32" context="$o73/child::s">
               <o id="o74" context="$s32/child::*[1][self::o][not(following-sibling::*)]">
                  <var id="f_1" context="$o74/child::*[1]">f</var>
                  <s id="s33"
                     context="$f_1/following-sibling::*[1][self::s][not(following-sibling::*)]">
                     <o id="o75"
                        context="$s33/child::*[1][self::o][not(following-sibling::*)][not(child::*)]"/>
                  </s>
               </o>
            </s>
            <q id="q21" context="$s32/following-sibling::*[1][self::q]">
               <var id="f_2" context="$q21/child::*[1]">f</var>
               <star id="star12"
                     context="$f_2/following-sibling::*[1][self::star][not(following-sibling::*)]">
                  <p id="p15" context="$star12/child::*[1][self::p][not(child::*)]"/>
                  <var id="c_1"
                       context="$p15/following-sibling::*[1][not(following-sibling::*)]">c</var>
               </star>
            </q>
            <seq id="h3_1"
                 xpath="$o73/child::*[position() &gt; $q21/count(preceding-sibling::*) + 1]">h3</seq>
         </o>    
      </lhs>
      <rhs>
         <o>
            <seq>h1</seq>
            <var>f</var>
            <s>
               <o> 
          </o>
            </s>
            <seq>h3</seq>
         </o>
      </rhs>
  </rewriteRule>
 


</algebra>
